README.md
main.py
pyproject.toml
mx_rec.egg-info/PKG-INFO
mx_rec.egg-info/SOURCES.txt
mx_rec.egg-info/dependency_links.txt
mx_rec.egg-info/top_level.txt