Metadata-Version: 2.4
Name: mx-rec
Version: 0.0.1.dev0
Summary: A fake package to warn the user they are not installing the correct package
Project-URL: Homepage, https://gitcode.com/Ascend/RecSDK
Project-URL: Repository, https://gitcode.com/Ascend/RecSDK.git
Requires-Python: >=3.7
